[
    {
        "usd": {
            "sell": "2.97",
            "buy": "2.974"
        }
    },
    {
        "eur": {
            "sell": "3.442",
            "buy": "3.449"
        }
    },
    {
        "rub": {
            "sell": "3.65",
            "buy": "3.66"
        }
    },
    {
        "pln": {
            "sell": "7.82",
            "buy": "8.05"
        }
    },
    {
        "uah": {
            "sell": "4.95",
            "buy": "5.93"
        }
    },
    {
        "gbp": {
            "sell": "3.845",
            "buy": "3.9"
        }
    },
    {
        "cny": {
            "sell": "4.27",
            "buy": "4.39"
        }
    },
    {
        "wrong": "Do not available on site"
    },
    {
        "kzt": {
            "sell": "5.2",
            "buy": "5.6"
        }
    },
    {
        "chf": {
            "sell": "3.425",
            "buy": "3.52"
        }
    },
    {
        "czk": {
            "sell": "13.4",
            "buy": "14.16"
        }
    },
    {
        "try": {
            "sell": "0.3",
            "buy": "0.94"
        }
    },
    {
        "gel": {
            "sell": "10.01",
            "buy": "12.79"
        }
    }
]